soliz/__init__.py
soliz/error.py
soliz/impls.py
soliz/lex.py
soliz/tokens.py
soliz-0.1.7.dist-info/LICENSE
soliz-0.1.7.dist-info/METADATA
soliz-0.1.7.dist-info/WHEEL
soliz-0.1.7.dist-info/top_level.txt
soliz-0.1.7.dist-info/RECORD
