Metadata-Version: 2.1
Name: soliz
Version: 0.1.7
Summary: A lexer creation tool
Author-email: Daniouz <gerbeebadoo@gmail.com>
Project-URL: Homepage, https://github.com/Daniouz/soliz
Project-URL: Issues, https://github.com/Daniouz/soliz/issues
Classifier: Programming Language :: Python :: 3
Classifier: License :: OSI Approved :: MIT License
Classifier: Operating System :: OS Independent
Requires-Python: >=3.8
License-File: LICENSE
